rapid_unwrap/__init__.py
rapid_unwrap/inference.py
rapid_unwrap/predictor.py
rapid_unwrap/models/.gitkeep
rapid_unwrap/utils/__init__.py
rapid_unwrap/utils/download_model.py
rapid_unwrap/utils/infer_engine.py
rapid_unwrap/utils/load_image.py
rapid_unwrap/utils/logger.py
rapid_unwrap-0.0.1.dist-info/METADATA
rapid_unwrap-0.0.1.dist-info/WHEEL
rapid_unwrap-0.0.1.dist-info/top_level.txt
rapid_unwrap-0.0.1.dist-info/RECORD
